wallstreet_judge/__init__.py
wallstreet_judge/data/auth.json
wallstreet_judge/data/holdings.json
wallstreet_judge/data/market.json
wallstreet_judge/data/orders.json
wallstreet_judge/data/sectors.json
wallstreet_judge/data/stocks.json
wallstreet_judge/main.py
wallstreet_judge/schema.py
wallstreet_judge/utils.py
wallstreet_judge-0.6.2.dist-info/entry_points.txt
wallstreet_judge-0.6.2.dist-info/WHEEL
wallstreet_judge-0.6.2.dist-info/METADATA
wallstreet_judge-0.6.2.dist-info/RECORD
